ctodd_python_lib_minio-1.0.2.dist-info/LICENSE.txt
ctodd_python_lib_minio-1.0.2.dist-info/METADATA
ctodd_python_lib_minio-1.0.2.dist-info/RECORD
ctodd_python_lib_minio-1.0.2.dist-info/WHEEL
ctodd_python_lib_minio-1.0.2.dist-info/top_level.txt
minio_helpers/__init__.py
minio_helpers/minio_bucket_helpers.py
minio_helpers/minio_client.py
minio_helpers/minio_connection_helpers.py
minio_helpers/minio_exceptions.py
minio_helpers/minio_general_helpers.py
minio_helpers/minio_object_helpers.py
minio_helpers/tests/__init__.py
minio_helpers/tests/test_minio_bucket_helpers.py
minio_helpers/tests/test_minio_client.py
minio_helpers/tests/test_minio_connection_helpers.py
minio_helpers/tests/test_minio_exceptions.py
minio_helpers/tests/test_minio_general_helpers.py
minio_helpers/tests/test_minio_object_helpers.py
